ethyca_fides-2.77.0.dist-info/licenses/LICENSE
fides/__init__.py
fides/_version.py
fides/py.typed
fides/api/__init__.py
fides/api/analytics.py
fides/api/app_setup.py
fides/api/common_exceptions.py
fides/api/custom_types.py
fides/api/main.py
fides/api/middleware.py
fides/api/request_context.py
fides/api/ui.py
fides/api/alembic/__init__.py
fides/api/alembic/alembic.ini
fides/api/alembic/migrations/__init__.py
fides/api/alembic/migrations/env.py
fides/api/alembic/migrations/helpers/__init__.py
fides/api/alembic/migrations/helpers/custom_report_migration_functions.py
fides/api/alembic/migrations/helpers/database_functions.py
fides/api/alembic/migrations/helpers/fideslang_migration_functions.py
fides/api/alembic/migrations/versions/0210948a8147_initial.py
fides/api/alembic/migrations/versions/021166731846_add_asset_table.py
fides/api/alembic/migrations/versions/021d288d0ce3_add_consent_request.py
fides/api/alembic/migrations/versions/07014ff34eb2_add_mariadb.py
fides/api/alembic/migrations/versions/093bb28a8270_add_plus_system_history_table.py
fides/api/alembic/migrations/versions/0c65325843bd_add_location_groups_column.py
fides/api/alembic/migrations/versions/0debabbb9c6a_add_property_config_and_css.py
fides/api/alembic/migrations/versions/0eef0016cf06_adding_oauth2_config_for_.py
fides/api/alembic/migrations/versions/1088e8353890_update_privacy_request_relationships.py
fides/api/alembic/migrations/versions/10c6b7709be3_adding_foreign_key_on_fides_key_for_.py
fides/api/alembic/migrations/versions/1152c1717849_fix_monitorexecution_started_default.py
fides/api/alembic/migrations/versions/1332815dcd71_purpose_header_to_translations.py
fides/api/alembic/migrations/versions/144d9b85c712_update_consent_mechanism.py
fides/api/alembic/migrations/versions/14acee6f5459_translation_data.py
fides/api/alembic/migrations/versions/150f234ef1de_add_fidesctl_meta_to_organization_object.py
fides/api/alembic/migrations/versions/155fd8e51d9d_add_fideslib_models.py
ethyca_fides-2.77.0.dist-info/METADATA
ethyca_fides-2.77.0.dist-info/WHEEL
ethyca_fides-2.77.0.dist-info/entry_points.txt
ethyca_fides-2.77.0.dist-info/top_level.txt
ethyca_fides-2.77.0.dist-info/RECORD
