Metadata-Version: 2.4
Name: ethyca_fides
Version: 2.77.0
Summary: Open-source ecosystem for data privacy as code.
Home-page: https://github.com/ethyca/fides
Author: Ethyca, Inc.
Author-email: fidesteam@ethyca.com
License: Apache License 2.0
Classifier: License :: OSI Approved :: Apache Software License
Classifier: Programming Language :: Python :: 3 :: Only
Classifier: Programming Language :: Python :: 3.9
Classifier: Programming Language :: Python :: 3.10
Classifier: Topic :: Software Development :: Libraries
Requires-Python: >=3.9, <4
License-File: LICENSE
Requires-Dist: acryl-datahub==0.14.1
Requires-Dist: alembic==1.8.1
Requires-Dist: anyascii==0.3.2
Requires-Dist: anyio==3.7.1
Requires-Dist: APScheduler==3.9.1.post1
Requires-Dist: asyncpg==0.27.0
Requires-Dist: boto3==1.26.1
Requires-Dist: certifi==2024.8.30
Requires-Dist: celery[pytest]==5.5.3
Requires-Dist: click==8.1.8
Requires-Dist: click_default_group==1.2.2
Requires-Dist: cloud-sql-python-connector==1.9.2
Requires-Dist: colorama>=0.4.3
Requires-Dist: cryptography==44.0.1
Requires-Dist: dask==2022.9.2
Requires-Dist: deepdiff==6.3.0
Requires-Dist: objgraph==3.6.0
Requires-Dist: defusedxml==0.7.1
Requires-Dist: types-defusedxml==0.7.0.20240218
Requires-Dist: expandvars==0.9.0
Requires-Dist: fastapi[all]==0.115.2
Requires-Dist: fastapi-pagination[sqlalchemy]==0.12.25
Requires-Dist: fideslog==1.2.15
Requires-Dist: firebase-admin==5.3.0
Requires-Dist: flower==2.0.1
Requires-Dist: GitPython==3.1.41
Requires-Dist: httpx==0.23.1
Requires-Dist: onepassword-sdk==0.3.0
Requires-Dist: iab-tcf==0.2.2
Requires-Dist: immutables==0.20
Requires-Dist: importlib_resources==5.12.0
Requires-Dist: Jinja2==3.1.5
Requires-Dist: joblib==1.3.2
Requires-Dist: loguru==0.6.0
Requires-Dist: multidimensional_urlencode==0.0.4
Requires-Dist: pg8000==1.31.2
Requires-Dist: nh3==0.2.15
Requires-Dist: numpy==1.24.4
Requires-Dist: oauthlib==3.3.1
Requires-Dist: openpyxl==3.0.9
Requires-Dist: networkx==3.1
Requires-Dist: packaging==23.0
Requires-Dist: pandas==1.4.3
Requires-Dist: paramiko==3.4.1
Requires-Dist: passlib[bcrypt]==1.7.4
Requires-Dist: pyinstrument==4.5.1
Requires-Dist: psycopg2-binary==2.9.6
Requires-Dist: pydantic==2.7.1
Requires-Dist: pydantic-settings==2.3.3
Requires-Dist: pydash==6.0.2
Requires-Dist: pygtrie==2.5.0
Requires-Dist: PyJWT==2.4.0
Requires-Dist: pymongo[srv]==4.7.3
Requires-Dist: PyMySQL==1.1.1
Requires-Dist: python-jose[cryptography]==3.3.0
Requires-Dist: pyyaml==6.0.1
Requires-Dist: pyahocorasick==2.1.0
Requires-Dist: redis==3.5.3
Requires-Dist: requests-oauth2client>=1.5.0
Requires-Dist: requests-oauthlib==2.0.0
Requires-Dist: rich-click==1.6.1
Requires-Dist: sendgrid==6.9.7
Requires-Dist: scylla-driver==3.26.8
Requires-Dist: slowapi==0.1.9
Requires-Dist: smart-open[gcs,s3]==7.3.0.post1
Requires-Dist: snowflake-sqlalchemy==1.5.1
Requires-Dist: sqlalchemy[asyncio]==1.4.27
Requires-Dist: sqlalchemy-citext==1.8.0
Requires-Dist: sqlalchemy-bigquery==1.7.0
Requires-Dist: sqlalchemy-redshift==0.8.11
Requires-Dist: sqlalchemy-stubs==0.4
Requires-Dist: SQLAlchemy-Utils==0.38.3
Requires-Dist: sshtunnel==0.4.0
Requires-Dist: stream-zip==0.0.83
Requires-Dist: tinycss2==1.2.1
Requires-Dist: toml==0.10.2
Requires-Dist: twilio==7.15.0
Requires-Dist: typing-extensions==4.12.2
Requires-Dist: versioneer==0.19
Requires-Dist: fideslang==3.1.2
Provides-Extra: mssql
Requires-Dist: pymssql==2.3.7; extra == "mssql"
Provides-Extra: all
Requires-Dist: pymssql==2.3.7; extra == "all"
Dynamic: author
Dynamic: author-email
Dynamic: classifier
Dynamic: description
Dynamic: description-content-type
Dynamic: home-page
Dynamic: license
Dynamic: license-file
Dynamic: provides-extra
Dynamic: requires-dist
Dynamic: requires-python
Dynamic: summary
